transgeo/__init__.py
transgeo/transgeo.py
transgeo-0.1.dist-info/METADATA
transgeo-0.1.dist-info/WHEEL
transgeo-0.1.dist-info/top_level.txt
transgeo-0.1.dist-info/RECORD
